[{"id":"PDMLOB2615527","unit_cost":92,"price":"#34.24","available_qty":58,"score":98,"company_name":"Bayer-Reilly","lead_time":1,"location":"San José","updated_time":"10-02-2022"},
{"id":"NYECL8728122","unit_cost":71,"price":"#69.8","available_qty":24,"score":73,"company_name":"Torp, Graham and Legros","lead_time":5,"location":"Fengjiang","updated_time":"05-03-2021"},
{"id":"MYPEOT5924657","unit_cost":89,"price":"#96.54","available_qty":61,"score":29,"company_name":"Conroy, Beatty and Haag","lead_time":2,"location":"Kitapak","updated_time":"10-09-2023"},
{"id":"DDPOI5420797","unit_cost":30,"price":"#77.43","available_qty":33,"score":69,"company_name":"Hansen LLC","lead_time":2,"location":"Rochester","updated_time":"25-05-2022"},
{"id":"YW5329005","unit_cost":29,"price":"#51.25","available_qty":83,"score":19,"company_name":"Crist LLC","lead_time":7,"location":"Yanjiang","updated_time":"22-06-2024"},
{"id":"GNCU4841389","unit_cost":22,"price":"#87.93","available_qty":74,"score":38,"company_name":"Schaden-Rempel","lead_time":8,"location":"Shiroi","updated_time":"16-11-2021"},
{"id":"XLC9772179","unit_cost":4,"price":"#58.86","available_qty":54,"score":70,"company_name":"Champlin, Heaney and Bayer","lead_time":6,"location":"Jammāl","updated_time":"23-05-2021"},
{"id":"EMS5379666","unit_cost":70,"price":"#48.89","available_qty":28,"score":96,"company_name":"Hamill, Schoen and McClure","lead_time":3,"location":"Vila Chã","updated_time":"04-03-2020"}]